{"chunk_definitions":[{"row":29,"row_count":1,"visible":true,"expansion_state":0,"options":{"column":"page","engine":"r","label":"unnamed-chunk-4"},"document_id":"5E48A2B7","chunk_id":"c7hj2hgd45yqa","chunk_label":"unnamed-chunk-1"},{"row":44,"row_count":1,"visible":true,"expansion_state":0,"options":{"column":"screen-inset-shaded","layout-nrow":1,"engine":"r","label":"unnamed-chunk-7"},"document_id":"5E48A2B7","chunk_id":"cxhomd22a9wdd","chunk_label":"unnamed-chunk-2"}],"doc_write_time":1723662607,"chunk_rendered_width":466}